gitchangelog/__init__.py
gitchangelog/gitchangelog.py
gitchangelog/gitchangelog.rc.reference
gitchangelog/gitchangelog.rc.reference.v2.1.3
gitchangelog/templates/mako/ChangeLog.tpl
gitchangelog/templates/mako/octobercms-plugin.tpl
gitchangelog/templates/mako/restructuredtext.tpl
gitchangelog/templates/mustache/markdown.tpl
gitchangelog/templates/mustache/restructuredtext.tpl
gitchangelog-3.0.4.dist-info/DESCRIPTION.rst
gitchangelog-3.0.4.dist-info/LICENSE.txt
gitchangelog-3.0.4.dist-info/METADATA
gitchangelog-3.0.4.dist-info/RECORD
gitchangelog-3.0.4.dist-info/WHEEL
gitchangelog-3.0.4.dist-info/entry_points.txt
gitchangelog-3.0.4.dist-info/metadata.json
gitchangelog-3.0.4.dist-info/top_level.txt
